md_sign/__init__.py
md_sign/main.py
md_sign-0.2.0.dist-info/LICENSE
md_sign-0.2.0.dist-info/METADATA
md_sign-0.2.0.dist-info/WHEEL
md_sign-0.2.0.dist-info/entry_points.txt
md_sign-0.2.0.dist-info/RECORD
