Metadata-Version: 2.1
Name: md-sign
Version: 0.2.0
Summary: Script to sign metadata
License: Apache 2
Author: Ivan Kanakarakis
Author-email: ivan.kanak@gmail.com
Requires-Python: >=3.7,<4.0
Classifier: License :: Other/Proprietary License
Classifier: Programming Language :: Python :: 3
Classifier: Programming Language :: Python :: 3.7
Classifier: Programming Language :: Python :: 3.8
Classifier: Programming Language :: Python :: 3.9
Classifier: Programming Language :: Python :: 3.10
Classifier: Programming Language :: Python :: 3.11
Requires-Dist: signxml (>=3,<4)
Requires-Dist: typer (>=0,<1)
